tabular_data/__init__.py
tabular_data/csv_file.py
tabular_data-0.1.4.dist-info/LICENSE
tabular_data-0.1.4.dist-info/WHEEL
tabular_data-0.1.4.dist-info/METADATA
tabular_data-0.1.4.dist-info/RECORD
