Metadata-Version: 2.1
Name: tabular-data
Version: 0.1.4
Summary: The sensible way to work with tabular data
Home-page: https://github.com/juanrgon/tabular-data
License: MIT
Author: Juan Gonzalez
Author-email: jrg2156@gmail.com
Requires-Python: >=3.10,<4.0
Classifier: License :: OSI Approved :: MIT License
Classifier: Programming Language :: Python :: 3
Classifier: Programming Language :: Python :: 3.10
Classifier: Programming Language :: Python :: 3.11
Requires-Dist: attrs (>=22.1.0,<23.0.0)
Project-URL: Repository, https://github.com/juanrgon/tabular-data
